CONTRIBUTING.md
MANIFEST.in
README.rst
setup.py
docs/HISTORY.txt
docs/LICENSE.GPL
docs/LICENSE.txt
eea/__init__.py
eea.forms.egg-info/PKG-INFO
eea.forms.egg-info/SOURCES.txt
eea.forms.egg-info/dependency_links.txt
eea.forms.egg-info/entry_points.txt
eea.forms.egg-info/namespace_packages.txt
eea.forms.egg-info/not-zip-safe
eea.forms.egg-info/requires.txt
eea.forms.egg-info/top_level.txt
eea/forms/README.txt
eea/forms/__init__.py
eea/forms/configure.zcml
eea/forms/profiles.zcml
eea/forms/skins.zcml
eea/forms/version.txt
eea/forms/browser/__init__.py
eea/forms/browser/configure.zcml
eea/forms/browser/app/__init__.py
eea/forms/browser/app/quick_upload.py
eea/forms/browser/app/temporal_coverage.py
eea/forms/browser/css/edit.css
eea/forms/browser/img/help.png
eea/forms/browser/js/edit.js
eea/forms/browser/js/quickupload.js
eea/forms/fields/ManagementPlanField.py
eea/forms/fields/__init__.py
eea/forms/locales/eea.pot
eea/forms/locales/update.sh
eea/forms/locales/bg/LC_MESSAGES/eea.po
eea/forms/locales/cs/LC_MESSAGES/eea.po
eea/forms/locales/da/LC_MESSAGES/eea.po
eea/forms/locales/de/LC_MESSAGES/eea.po
eea/forms/locales/el/LC_MESSAGES/eea.po
eea/forms/locales/en/LC_MESSAGES/eea.po
eea/forms/locales/es/LC_MESSAGES/eea.po
eea/forms/locales/et/LC_MESSAGES/eea.po
eea/forms/locales/eu/LC_MESSAGES/eea.po
eea/forms/locales/fi/LC_MESSAGES/eea.po
eea/forms/locales/fr/LC_MESSAGES/eea.po
eea/forms/locales/hu/LC_MESSAGES/eea.po
eea/forms/locales/is/LC_MESSAGES/eea.po
eea/forms/locales/it/LC_MESSAGES/eea.po
eea/forms/locales/kl/LC_MESSAGES/eea.po
eea/forms/locales/lt/LC_MESSAGES/eea.po
eea/forms/locales/lv/LC_MESSAGES/eea.po
eea/forms/locales/mt/LC_MESSAGES/eea.po
eea/forms/locales/nl/LC_MESSAGES/eea.po
eea/forms/locales/no/LC_MESSAGES/eea.po
eea/forms/locales/pl/LC_MESSAGES/eea.po
eea/forms/locales/pt/LC_MESSAGES/eea.po
eea/forms/locales/pt_BR/LC_MESSAGES/eea.po
eea/forms/locales/ro/LC_MESSAGES/eea.po
eea/forms/locales/ru/LC_MESSAGES/eea.po
eea/forms/locales/sk/LC_MESSAGES/eea.po
eea/forms/locales/sl/LC_MESSAGES/eea.po
eea/forms/locales/sv/LC_MESSAGES/eea.po
eea/forms/locales/tr/LC_MESSAGES/eea.po
eea/forms/locales/zh_TW/LC_MESSAGES/eea.po
eea/forms/profiles/default/cssregistry.xml
eea/forms/profiles/default/jsregistry.xml
